{
  "generated_at": "2026-07-13T11:43:31.679239+08:00",
  "generated_at_display": "Jul 13, 2026 · 11:43 AM HKT",
  "cards": [
    {
      "rank": 1,
      "title": "England on collision course with Messi and Argentina in World Cup semi-final grudge match",
      "source": "The Guardian",
      "virality_score": 59,
      "pub_ago": "7h ago",
      "teams": [
        "Argentina",
        "England"
      ],
      "files": {
        "916": "cards/20260713_1143_card1_916.png",
        "169": "cards/20260713_1143_card1_169.png"
      }
    },
    {
      "rank": 2,
      "title": "Tuchel and Bellingham need to cool tension with England so close to history | Jacob Steinberg",
      "source": "The Guardian",
      "virality_score": 52,
      "pub_ago": "9h ago",
      "teams": [
        "England"
      ],
      "files": {
        "916": "cards/20260713_1143_card2_916.png",
        "169": "cards/20260713_1143_card2_169.png"
      }
    },
    {
      "rank": 3,
      "title": "'We have another level we can reach' - Kane defends frustrated Tuchel",
      "source": "BBC Sport",
      "virality_score": 49,
      "pub_ago": "9h ago",
      "teams": [
        "England"
      ],
      "files": {
        "916": "cards/20260713_1143_card3_916.png",
        "169": "cards/20260713_1143_card3_169.png"
      }
    }
  ]
}